alpyvantage/__init__.py
alpyvantage/__version__.py
alpyvantage/data_formating.py
alpyvantage/test_all.py
alpyvantage-0.2.1.dist-info/LICENSE
alpyvantage-0.2.1.dist-info/METADATA
alpyvantage-0.2.1.dist-info/WHEEL
alpyvantage-0.2.1.dist-info/top_level.txt
alpyvantage-0.2.1.dist-info/RECORD
