Metadata-Version: 2.1
Name: alpyvantage
Version: 0.2.1
Summary: A python API to Alpha Vantage
Home-page: https://github.com/gboehl/alpyvantage
Author: Gregor Boehl
Author-email: admin@gregorboehl.com
License: MIT
Classifier: License :: OSI Approved :: MIT License
Classifier: Programming Language :: Python :: 3
Classifier: Programming Language :: Python :: 3.9
License-File: LICENSE
Requires-Dist: pandas
Requires-Dist: requests
